{ "name": "UC5/NoLoadFlexOb0",
  "scenario_settings": {
            "network": "MV Oberrhein0",
            "dp": 0.068,
            "dq": 0.068,
            "v_sens": 0.0001,
            "resolution": 10,
            "distribution": "Thorough",
            "TTD": false,
            "keep_mp": false,
            "max_curr_per": 100,
            "max_volt_pu": 1.05,
            "min_volt_pu": 0.95,
            "Convolution_simulation": true,
            "accuracy": false,
            "ground_truth_file": "Flexibility_area_Unaltered_Model_Scenario",
            "multiplicity": true,
            "uncertainty": false,
            "save_tensors": false,
            "adapt": false,
            "FSPs": "All",
            "FSP_load_indices": [18, 22],
            "FSP_DG_indices": [26, 50],
            "Non-Linear DGs": [],
            "observable_lines_indices": [0, 1, 10, 11],
            "observable_buses_indices": [0, 1, 2, 3, 12, 13, 14],
            "scenario_type": {"name": "CS",
                              "std_cap_ld": 0.2,
                              "std_cap_dg": 0.2,
                              "std_pf_ld": 0.0,
                              "std_pf_dg": 0.0,
                              "no.": 103},
            "plot_settings": {"convex_hull": false,
                              "plot_combination": false,
                              "multiplicity": false,
                              "convolution": true,
                              "filenames" : [],
                              "output type": "png"
            }
  }
}